mircat_stats/__init__.py
mircat_stats/configs/__init__.py
mircat_stats/configs/logging.py
mircat_stats/configs/models.py
mircat_stats/configs/statistics.py
mircat_stats/dicom/__init__.py
mircat_stats/dicom/dicom_folder.py
mircat_stats/models/__init__.py
mircat_stats/models/xgboost.json
mircat_stats/statistics/__init__.py
mircat_stats/statistics/aorta.py
mircat_stats/statistics/body_and_tissues.py
mircat_stats/statistics/centerline.py
mircat_stats/statistics/contrast_detection.py
mircat_stats/statistics/cpr.py
mircat_stats/statistics/heart.py
mircat_stats/statistics/nifti.py
mircat_stats/statistics/segmentation.py
mircat_stats/statistics/total.py
mircat_stats/statistics/utils.py
mircat_stats-1.0.0.dist-info/METADATA
mircat_stats-1.0.0.dist-info/WHEEL
mircat_stats-1.0.0.dist-info/entry_points.txt
mircat_stats-1.0.0.dist-info/RECORD
